<?xml version="1.0" encoding="utf-8" ?><dwsync><file name="asks.htm" server="cigia.gotoftp3.com/wwwroot/" local="3392352898" remote="7784899336" Dst="-1" /><file name="bookcontentlist.htm" server="cigia.gotoftp3.com/wwwroot/" local="3392352898" remote="-4611698624961436920" Dst="-1" /><file name="booklist.htm" server="cigia.gotoftp3.com/wwwroot/" local="3392352898" remote="-4611698624961436920" Dst="-1" /><file name="channel_addon.htm" server="cigia.gotoftp3.com/wwwroot/" local="3392352898" remote="-4611698624961436920" Dst="-1" /><file name="channel_article_image.htm" server="cigia.gotoftp3.com/wwwroot/" local="3392352898" remote="-4611698624961436920" Dst="-1" /><file name="channel_downlinkpage.htm" server="cigia.gotoftp3.com/wwwroot/" local="3392352898" remote="-4611698624961436920" Dst="-1" /><file name="channel_downlinks.htm" server="cigia.gotoftp3.com/wwwroot/" local="3392352898" remote="-4611698624961436920" Dst="-1" /><file name="channel_spec_note.htm" server="cigia.gotoftp3.com/wwwroot/" local="3392352898" remote="-4611698624961436920" Dst="-1" /><file name="channel_list.htm" server="cigia.gotoftp3.com/wwwroot/" local="3392352898" remote="-4611698624961436920" Dst="-1" /><file name="custom_fields_admin.htm" server="cigia.gotoftp3.com/wwwroot/" local="3392352898" remote="-4611698624961436920" Dst="-1" /><file name="custom_fields_diy.htm" server="cigia.gotoftp3.com/wwwroot/" local="3392352898" remote="-4611698624961436920" Dst="-1" /><file name="custom_fields_member.htm" server="cigia.gotoftp3.com/wwwroot/" local="3392352898" remote="-4611698624961436920" Dst="-1" /><file name="custom_fields_membermodel.htm" server="cigia.gotoftp3.com/wwwroot/" local="3392352898" remote="-4611698624961436920" Dst="-1" /><file name="custom_fields_membermodel2.htm" server="cigia.gotoftp3.com/wwwroot/" local="3392352898" remote="-4611698624961436920" Dst="-1" /><file name="groups.htm" server="cigia.gotoftp3.com/wwwroot/" local="3392352898" remote="-4611698624961436920" Dst="-1" /><file name="groupthreads.htm" server="cigia.gotoftp3.com/wwwroot/" local="3392352898" remote="-4611698624961436920" Dst="-1" /><file name="info_guide.htm" server="cigia.gotoftp3.com/wwwroot/" local="3392352898" remote="-4611698624961436920" Dst="-1" /><file name="info_link.htm" server="cigia.gotoftp3.com/wwwroot/" local="3392352898" remote="-4611698624961436920" Dst="-1" /><file name="list_fulllist.htm" server="cigia.gotoftp3.com/wwwroot/" local="3392352898" remote="7784899336" Dst="-1" /><file name="list_sglist.htm" server="cigia.gotoftp3.com/wwwroot/" local="3392352898" remote="-4611698624961436920" Dst="-1" /><file name="memberinfos.htm" server="cigia.gotoftp3.com/wwwroot/" local="3392352898" remote="-4611698624961436920" Dst="-1" /><file name="memberlist.htm" server="cigia.gotoftp3.com/wwwroot/" local="3392352898" remote="-4611698624961436920" Dst="-1" /><file name="mynews.htm" server="cigia.gotoftp3.com/wwwroot/" local="3392352900" remote="-4611698624961436920" Dst="-1" /><file name="part_arclist.htm" server="cigia.gotoftp3.com/wwwroot/" local="3392352900" remote="-4611698624961436920" Dst="-1" /><file name="part_arclistsg.htm" server="cigia.gotoftp3.com/wwwroot/" local="3392352900" remote="-4611698624961436920" Dst="-1" /><file name="part_autochannel.htm" server="cigia.gotoftp3.com/wwwroot/" local="3392352900" remote="-4611698624961436920" Dst="-1" /><file name="part_channelartlist.htm" server="cigia.gotoftp3.com/wwwroot/" local="3392352900" remote="-4611698624961436920" Dst="-1" /><file name="part_imginfolist.htm" server="cigia.gotoftp3.com/wwwroot/" local="3392352900" remote="-4611698624961436920" Dst="-1" /><file name="part_imglist.htm" server="cigia.gotoftp3.com/wwwroot/" local="3392352900" remote="-4611698624961436920" Dst="-1" /><file name="part_type_list.htm" server="cigia.gotoftp3.com/wwwroot/" local="3392352900" remote="-4611698624961436920" Dst="-1" /><file name="spec_arclist.htm" server="cigia.gotoftp3.com/wwwroot/" local="3392352900" remote="-4611698624961436920" Dst="-1" /><file name="spec_list.htm" server="cigia.gotoftp3.com/wwwroot/" local="3392352900" remote="-4611698624961436920" Dst="-1" /><file name="tag_arclist.htm" server="cigia.gotoftp3.com/wwwroot/" local="3392352900" remote="-4611698624961436920" Dst="-1" /><file name="tag_feedback.htm" server="cigia.gotoftp3.com/wwwroot/" local="3392352900" remote="-4611698624961436920" Dst="-1" /><file name="tag_fieldlist.htm" server="cigia.gotoftp3.com/wwwroot/" local="3392352900" remote="-4611698624961436920" Dst="-1" /><file name="tag_likepage.htm" server="cigia.gotoftp3.com/wwwroot/" local="3392352900" remote="-4611698624961436920" Dst="-1" /><file name="tag_likesgpage.htm" server="cigia.gotoftp3.com/wwwroot/" local="3392352900" remote="-4611698624961436920" Dst="-1" /><file name="tag_one.htm" server="cigia.gotoftp3.com/wwwroot/" local="3392352900" remote="-4611698624961436920" Dst="-1" /></dwsync>